{"format_version":"1.2","terraform_version":"1.10.7","variables":{"cluster_yaml_path":{"value":"../test/../path/../test_cluster.yaml"},"credentials_file":{"value":"../test/../path/../credentials_file.json"},"hostname":{"value":"test_hostname"},"init_check_script":{"value":"../test/../path/../run_initialization_checks.sh"},"init_logs":{"value":"test_init_log_file.log"},"init_script":{"value":"../test/../path/../init_script.sh"},"init_vars_file":{"value":"../test/../path/../init_vars_file.var"},"install_abm_script":{"value":"../../resources/install_abm.sh"},"login_script":{"value":"../../resources/login.sh"},"module_depends_on":{"value":[]},"nfs_yaml_path":{"value":"../test/../path/../test_nfs-csi.yaml"},"priv_key_path_template":{"value":"../test/../path/../test_pub_key-%s.priv"},"project_id":{"value":"test_project"},"pub_key_path_template":{"value":"../test/../path/../test_pub_key-%s.pub"},"publicIp":{"value":"10.10.10.01"},"resources_path":{"value":"../../resources"},"username":{"value":"test_username"},"zone":{"value":"test_zone"}},"planned_values":{"root_module":{"resources":[{"address":"local_file.temp_ssh_priv_key_file","mode":"managed","type":"local_file","name":"temp_ssh_priv_key_file","provider_name":"registry.opentofu.org/hashicorp/local","schema_version":0,"values":{"content_base64":null,"directory_permission":"0777","file_permission":"0600","filename":"../test/../path/../test_pub_key-test_hostname.priv","sensitive_content":null,"source":null},"sensitive_values":{"content":true,"sensitive_content":true}},{"address":"local_file.temp_ssh_pub_key_file","mode":"managed","type":"local_file","name":"temp_ssh_pub_key_file","provider_name":"registry.opentofu.org/hashicorp/local","schema_version":0,"values":{"content_base64":null,"directory_permission":"0777","file_permission":"0600","filename":"../test/../path/../test_pub_key-test_hostname.pub","sensitive_content":null,"source":null},"sensitive_values":{"sensitive_content":true}},{"address":"null_resource.exec_init_script","mode":"managed","type":"null_resource","name":"exec_init_script","provider_name":"registry.opentofu.org/hashicorp/null","schema_version":0,"values":{"triggers":null},"sensitive_values":{}},{"address":"tls_private_key.ssh_key_pair","mode":"managed","type":"tls_private_key","name":"ssh_key_pair","provider_name":"registry.opentofu.org/hashicorp/tls","schema_version":1,"values":{"algorithm":"RSA","ecdsa_curve":"P224","rsa_bits":4096},"sensitive_values":{"private_key_openssh":true,"private_key_pem":true,"private_key_pem_pkcs8":true}}],"child_modules":[{"resources":[{"address":"module.gcloud_add_ssh_key_metadata.null_resource.module_depends_on[0]","mode":"managed","type":"null_resource","name":"module_depends_on","index":0,"provider_name":"registry.opentofu.org/hashicorp/null","schema_version":0,"values":{"triggers":{"value":"2"}},"sensitive_values":{"triggers":{}}},{"address":"module.gcloud_add_ssh_key_metadata.null_resource.run_command[0]","mode":"managed","type":"null_resource","name":"run_command","index":0,"provider_name":"registry.opentofu.org/hashicorp/null","schema_version":0,"values":{"triggers":{"arguments":"db4d2a4cbf17f9a34cc871ada33a07db","create_cmd_body":"    compute instances add-metadata test_hostname  \\\n    --project test_project                                    \\\n    --zone test_zone                                             \\\n    --metadata-from-file ssh-keys=../test/../path/../test_pub_key-test_hostname.pub\n","create_cmd_entrypoint":"gcloud","gcloud_bin_abs_path":"/google-cloud-sdk/bin","md5":"7f22bf39aaf5ce5980111c3587bef5b5"}},"sensitive_values":{"triggers":{}}},{"address":"module.gcloud_add_ssh_key_metadata.null_resource.run_destroy_command[0]","mode":"managed","type":"null_resource","name":"run_destroy_command","index":0,"provider_name":"registry.opentofu.org/hashicorp/null","schema_version":0,"values":{"triggers":{"destroy_cmd_body":"info","destroy_cmd_entrypoint":"gcloud","gcloud_bin_abs_path":"/google-cloud-sdk/bin"}},"sensitive_values":{"triggers":{}}}],"address":"module.gcloud_add_ssh_key_metadata"}]}},"resource_changes":[{"address":"local_file.temp_ssh_priv_key_file","mode":"managed","type":"local_file","name":"temp_ssh_priv_key_file","provider_name":"registry.opentofu.org/hashicorp/local","change":{"actions":["create"],"before":null,"after":{"content_base64":null,"directory_permission":"0777","file_permission":"0600","filename":"../test/../path/../test_pub_key-test_hostname.priv","sensitive_content":null,"source":null},"after_unknown":{"content":true,"content_base64sha256":true,"content_base64sha512":true,"content_md5":true,"content_sha1":true,"content_sha256":true,"content_sha512":true,"id":true},"before_sensitive":false,"after_sensitive":{"content":true,"sensitive_content":true}}},{"address":"local_file.temp_ssh_pub_key_file","mode":"managed","type":"local_file","name":"temp_ssh_pub_key_file","provider_name":"registry.opentofu.org/hashicorp/local","change":{"actions":["create"],"before":null,"after":{"content_base64":null,"directory_permission":"0777","file_permission":"0600","filename":"../test/../path/../test_pub_key-test_hostname.pub","sensitive_content":null,"source":null},"after_unknown":{"content":true,"content_base64sha256":true,"content_base64sha512":true,"content_md5":true,"content_sha1":true,"content_sha256":true,"content_sha512":true,"id":true},"before_sensitive":false,"after_sensitive":{"sensitive_content":true}}},{"address":"null_resource.exec_init_script","mode":"managed","type":"null_resource","name":"exec_init_script","provider_name":"registry.opentofu.org/hashicorp/null","change":{"actions":["create"],"before":null,"after":{"triggers":null},"after_unknown":{"id":true},"before_sensitive":false,"after_sensitive":{}}},{"address":"tls_private_key.ssh_key_pair","mode":"managed","type":"tls_private_key","name":"ssh_key_pair","provider_name":"registry.opentofu.org/hashicorp/tls","change":{"actions":["create"],"before":null,"after":{"algorithm":"RSA","ecdsa_curve":"P224","rsa_bits":4096},"after_unknown":{"id":true,"private_key_openssh":true,"private_key_pem":true,"private_key_pem_pkcs8":true,"public_key_fingerprint_md5":true,"public_key_fingerprint_sha256":true,"public_key_openssh":true,"public_key_pem":true},"before_sensitive":false,"after_sensitive":{"private_key_openssh":true,"private_key_pem":true,"private_key_pem_pkcs8":true}}},{"address":"module.gcloud_add_ssh_key_metadata.null_resource.module_depends_on[0]","module_address":"module.gcloud_add_ssh_key_metadata","mode":"managed","type":"null_resource","name":"module_depends_on","index":0,"provider_name":"registry.opentofu.org/hashicorp/null","change":{"actions":["create"],"before":null,"after":{"triggers":{"value":"2"}},"after_unknown":{"id":true,"triggers":{}},"before_sensitive":false,"after_sensitive":{"triggers":{}}}},{"address":"module.gcloud_add_ssh_key_metadata.null_resource.run_command[0]","module_address":"module.gcloud_add_ssh_key_metadata","mode":"managed","type":"null_resource","name":"run_command","index":0,"provider_name":"registry.opentofu.org/hashicorp/null","change":{"actions":["create"],"before":null,"after":{"triggers":{"arguments":"db4d2a4cbf17f9a34cc871ada33a07db","create_cmd_body":"    compute instances add-metadata test_hostname  \\\n    --project test_project                                    \\\n    --zone test_zone                                             \\\n    --metadata-from-file ssh-keys=../test/../path/../test_pub_key-test_hostname.pub\n","create_cmd_entrypoint":"gcloud","gcloud_bin_abs_path":"/google-cloud-sdk/bin","md5":"7f22bf39aaf5ce5980111c3587bef5b5"}},"after_unknown":{"id":true,"triggers":{}},"before_sensitive":false,"after_sensitive":{"triggers":{}}}},{"address":"module.gcloud_add_ssh_key_metadata.null_resource.run_destroy_command[0]","module_address":"module.gcloud_add_ssh_key_metadata","mode":"managed","type":"null_resource","name":"run_destroy_command","index":0,"provider_name":"registry.opentofu.org/hashicorp/null","change":{"actions":["create"],"before":null,"after":{"triggers":{"destroy_cmd_body":"info","destroy_cmd_entrypoint":"gcloud","gcloud_bin_abs_path":"/google-cloud-sdk/bin"}},"after_unknown":{"id":true,"triggers":{}},"before_sensitive":false,"after_sensitive":{"triggers":{}}}}],"prior_state":{"format_version":"1.0","terraform_version":"1.10.7","values":{"root_module":{"child_modules":[{"resources":[{"address":"module.gcloud_add_ssh_key_metadata.data.external.env_override[0]","mode":"data","type":"external","name":"env_override","index":0,"provider_name":"registry.opentofu.org/hashicorp/external","schema_version":0,"values":{"id":"-","program":[".terraform/modules/gcloud_add_ssh_key_metadata/scripts/check_env.sh"],"query":{},"result":{"download":""},"working_dir":null},"sensitive_values":{"program":[false],"query":{},"result":{}}}],"address":"module.gcloud_add_ssh_key_metadata"}]}}},"configuration":{"provider_config":{"local":{"name":"local","full_name":"registry.opentofu.org/hashicorp/local"},"module.gcloud_add_ssh_key_metadata:external":{"name":"external","full_name":"registry.opentofu.org/hashicorp/external","version_constraint":"\u003e= 2.2.2","module_address":"module.gcloud_add_ssh_key_metadata"},"module.gcloud_add_ssh_key_metadata:google":{"name":"google","full_name":"registry.opentofu.org/hashicorp/google","version_constraint":"\u003e= 3.53.0, \u003c 7.0.0","module_address":"module.gcloud_add_ssh_key_metadata"},"module.gcloud_add_ssh_key_metadata:random":{"name":"random","full_name":"registry.opentofu.org/hashicorp/random","version_constraint":"\u003e= 2.1.0","module_address":"module.gcloud_add_ssh_key_metadata"},"null":{"name":"null","full_name":"registry.opentofu.org/hashicorp/null"},"tls":{"name":"tls","full_name":"registry.opentofu.org/hashicorp/tls"}},"root_module":{"resources":[{"address":"local_file.temp_ssh_priv_key_file","mode":"managed","type":"local_file","name":"temp_ssh_priv_key_file","provider_config_key":"local","expressions":{"content":{"references":["tls_private_key.ssh_key_pair.private_key_pem","tls_private_key.ssh_key_pair"]},"file_permission":{"constant_value":"0600"},"filename":{"references":["local.ssh_private_key_file"]}},"schema_version":0},{"address":"local_file.temp_ssh_pub_key_file","mode":"managed","type":"local_file","name":"temp_ssh_pub_key_file","provider_config_key":"local","expressions":{"content":{"references":["local.ssh_pub_key_template_file","var.username","tls_private_key.ssh_key_pair.public_key_openssh","tls_private_key.ssh_key_pair"]},"file_permission":{"constant_value":"0600"},"filename":{"references":["local.ssh_pub_key_file"]}},"schema_version":0},{"address":"null_resource.exec_init_script","mode":"managed","type":"null_resource","name":"exec_init_script","provider_config_key":"null","provisioners":[{"type":"file","expressions":{"destination":{"references":["local.home_dir","local.cluster_yaml_file_name"]},"source":{"references":["var.cluster_yaml_path"]}}},{"type":"file","expressions":{"destination":{"references":["local.home_dir"]},"source":{"references":["var.init_vars_file"]}}},{"type":"file","expressions":{"destination":{"references":["local.home_dir"]},"source":{"references":["var.init_script"]}}},{"type":"file","expressions":{"destination":{"references":["local.home_dir"]},"source":{"references":["var.init_check_script"]}}},{"type":"file","expressions":{"destination":{"references":["local.home_dir"]},"source":{"references":["var.install_abm_script"]}}},{"type":"file","expressions":{"destination":{"references":["local.home_dir"]},"source":{"references":["var.login_script"]}}},{"type":"file","expressions":{"destination":{"references":["local.home_dir"]},"source":{"references":["var.nfs_yaml_path"]}}},{"type":"remote-exec","expressions":{"inline":{"references":["local.home_dir","local.cluster_yaml_file_name","local.home_dir","local.home_dir","local.home_dir","local.home_dir","local.home_dir"]}}},{"type":"local-exec","expressions":{"command":{"references":["local.ssh_private_key_file","var.username","var.publicIp","local.home_dir","local.home_dir","var.init_logs"]},"interpreter":{"constant_value":["/bin/bash","-c"]}}}],"schema_version":0,"depends_on":["module.gcloud_add_ssh_key_metadata","null_resource.module_depends_on"]},{"address":"null_resource.module_depends_on","mode":"managed","type":"null_resource","name":"module_depends_on","provider_config_key":"null","expressions":{"triggers":{"references":["var.module_depends_on"]}},"schema_version":0,"count_expression":{"references":["var.module_depends_on"]}},{"address":"tls_private_key.ssh_key_pair","mode":"managed","type":"tls_private_key","name":"ssh_key_pair","provider_config_key":"tls","expressions":{"algorithm":{"constant_value":"RSA"},"rsa_bits":{"constant_value":4096}},"schema_version":1}],"module_calls":{"gcloud_add_ssh_key_metadata":{"source":"terraform-google-modules/gcloud/google","expressions":{"create_cmd_body":{"references":["var.hostname","var.project_id","var.zone","local.ssh_pub_key_file"]},"create_cmd_entrypoint":{"constant_value":"gcloud"},"module_depends_on":{"references":["local_file.temp_ssh_pub_key_file","local_file.temp_ssh_priv_key_file"]},"platform":{"constant_value":"linux"}},"module":{"outputs":{"bin_dir":{"expression":{"references":["local.gcloud_bin_path"]},"description":"The full bin path of the modules executables"},"create_cmd_bin":{"expression":{"references":["local.create_cmd_bin"]},"description":"The full bin path \u0026 command used on create"},"destroy_cmd_bin":{"expression":{"references":["local.destroy_cmd_bin"]},"description":"The full bin path \u0026 command used on destroy"},"downloaded":{"expression":{"references":["local.skip_download"]},"depends_on":["local.wait"],"description":"Whether gcloud was downloaded or not"},"wait":{"expression":{"references":["local.wait"]},"description":"An output to use when you want to depend on cmd finishing"}},"resources":[{"address":"null_resource.additional_components","mode":"managed","type":"null_resource","name":"additional_components","provider_config_key":"null","provisioners":[{"type":"local-exec","expressions":{"command":{"references":["self.triggers.additional_components_command","self.triggers","self"]}}}],"expressions":{"triggers":{"references":["var.create_cmd_entrypoint","var.create_cmd_body","local.additional_components_command","var.create_cmd_triggers"]}},"schema_version":0,"count_expression":{"references":["var.enabled","var.additional_components"]},"depends_on":["null_resource.decompress","null_resource.upgrade"]},{"address":"null_resource.additional_components_destroy","mode":"managed","type":"null_resource","name":"additional_components_destroy","provider_config_key":"null","provisioners":[{"type":"local-exec","expressions":{"command":{"references":["self.triggers.additional_components_command","self.triggers","self"]}}}],"expressions":{"triggers":{"references":["local.additional_components_command"]}},"schema_version":0,"count_expression":{"references":["var.enabled","var.additional_components"]},"depends_on":["null_resource.run_destroy_command"]},{"address":"null_resource.decompress","mode":"managed","type":"null_resource","name":"decompress","provider_config_key":"null","provisioners":[{"type":"local-exec","expressions":{"command":{"references":["self.triggers.decompress_command","self.triggers","self"]}}}],"expressions":{"triggers":{"references":["var.create_cmd_entrypoint","var.create_cmd_body","local.decompress_command","local.download_gcloud_command","local.download_jq_command","var.create_cmd_triggers"]}},"schema_version":0,"count_expression":{"references":["var.enabled","local.skip_download"]},"depends_on":["null_resource.download_gcloud","null_resource.download_jq"]},{"address":"null_resource.decompress_destroy","mode":"managed","type":"null_resource","name":"decompress_destroy","provider_config_key":"null","provisioners":[{"type":"local-exec","expressions":{"command":{"references":["self.triggers.decompress_wrapper","self.triggers","self"]}}}],"expressions":{"triggers":{"references":["local.decompress_wrapper"]}},"schema_version":0,"count_expression":{"references":["var.enabled","local.skip_download"]},"depends_on":["null_resource.upgrade_destroy"]},{"address":"null_resource.download_gcloud","mode":"managed","type":"null_resource","name":"download_gcloud","provider_config_key":"null","provisioners":[{"type":"local-exec","expressions":{"command":{"references":["self.triggers.download_gcloud_command","self.triggers","self"]}}}],"expressions":{"triggers":{"references":["var.create_cmd_entrypoint","var.create_cmd_body","local.download_gcloud_command","var.create_cmd_triggers"]}},"schema_version":0,"count_expression":{"references":["var.enabled","local.skip_download"]},"depends_on":["null_resource.prepare_cache"]},{"address":"null_resource.download_jq","mode":"managed","type":"null_resource","name":"download_jq","provider_config_key":"null","provisioners":[{"type":"local-exec","expressions":{"command":{"references":["self.triggers.download_jq_command","self.triggers","self"]}}}],"expressions":{"triggers":{"references":["var.create_cmd_entrypoint","var.create_cmd_body","local.download_jq_command","var.create_cmd_triggers"]}},"schema_version":0,"count_expression":{"references":["var.enabled","local.skip_download"]},"depends_on":["null_resource.prepare_cache"]},{"address":"null_resource.gcloud_auth_google_credentials","mode":"managed","type":"null_resource","name":"gcloud_auth_google_credentials","provider_config_key":"null","provisioners":[{"type":"local-exec","expressions":{"command":{"references":["self.triggers.gcloud_auth_google_credentials_command","self.triggers","self"]}}}],"expressions":{"triggers":{"references":["var.create_cmd_entrypoint","var.create_cmd_body","local.gcloud_auth_google_credentials_command","var.create_cmd_triggers"]}},"schema_version":0,"count_expression":{"references":["var.enabled","var.use_tf_google_credentials_env_var"]},"depends_on":["null_resource.decompress","null_resource.upgrade"]},{"address":"null_resource.gcloud_auth_google_credentials_destroy","mode":"managed","type":"null_resource","name":"gcloud_auth_google_credentials_destroy","provider_config_key":"null","provisioners":[{"type":"local-exec","expressions":{"command":{"references":["self.triggers.gcloud_auth_google_credentials_command","self.triggers","self"]}}}],"expressions":{"triggers":{"references":["local.gcloud_auth_google_credentials_command"]}},"schema_version":0,"count_expression":{"references":["var.enabled","var.use_tf_google_credentials_env_var"]},"depends_on":["null_resource.run_destroy_command"]},{"address":"null_resource.gcloud_auth_service_account_key_file","mode":"managed","type":"null_resource","name":"gcloud_auth_service_account_key_file","provider_config_key":"null","provisioners":[{"type":"local-exec","expressions":{"command":{"references":["self.triggers.gcloud_auth_service_account_key_file_command","self.triggers","self"]}}}],"expressions":{"triggers":{"references":["var.create_cmd_entrypoint","var.create_cmd_body","local.gcloud_auth_service_account_key_file_command","var.create_cmd_triggers"]}},"schema_version":0,"count_expression":{"references":["var.enabled","var.service_account_key_file"]},"depends_on":["null_resource.decompress","null_resource.upgrade"]},{"address":"null_resource.gcloud_auth_service_account_key_file_destroy","mode":"managed","type":"null_resource","name":"gcloud_auth_service_account_key_file_destroy","provider_config_key":"null","provisioners":[{"type":"local-exec","expressions":{"command":{"references":["self.triggers.gcloud_auth_service_account_key_file_command","self.triggers","self"]}}}],"expressions":{"triggers":{"references":["local.gcloud_auth_service_account_key_file_command"]}},"schema_version":0,"count_expression":{"references":["var.enabled","var.service_account_key_file"]},"depends_on":["null_resource.run_destroy_command"]},{"address":"null_resource.module_depends_on","mode":"managed","type":"null_resource","name":"module_depends_on","provider_config_key":"null","expressions":{"triggers":{"references":["var.module_depends_on"]}},"schema_version":0,"count_expression":{"references":["var.module_depends_on"]}},{"address":"null_resource.prepare_cache","mode":"managed","type":"null_resource","name":"prepare_cache","provider_config_key":"null","provisioners":[{"type":"local-exec","expressions":{"command":{"references":["self.triggers.prepare_cache_command","self.triggers","self"]}}}],"expressions":{"triggers":{"references":["var.create_cmd_entrypoint","var.create_cmd_body","local.prepare_cache_command","var.create_cmd_triggers"]}},"schema_version":0,"count_expression":{"references":["var.enabled","local.skip_download"]},"depends_on":["null_resource.module_depends_on"]},{"address":"null_resource.run_command","mode":"managed","type":"null_resource","name":"run_command","provider_config_key":"null","provisioners":[{"type":"local-exec","expressions":{"command":{"references":["self.triggers.gcloud_bin_abs_path","self.triggers","self","self.triggers.create_cmd_entrypoint","self.triggers","self","self.triggers.create_cmd_body","self.triggers","self"]}}}],"expressions":{"triggers":{"references":["var.create_cmd_entrypoint","var.create_cmd_body","var.create_cmd_entrypoint","var.create_cmd_body","local.gcloud_bin_abs_path","var.create_cmd_triggers"]}},"schema_version":0,"count_expression":{"references":["var.enabled"]},"depends_on":["null_resource.module_depends_on","null_resource.decompress","null_resource.additional_components","null_resource.gcloud_auth_google_credentials","null_resource.gcloud_auth_service_account_key_file"]},{"address":"null_resource.run_destroy_command","mode":"managed","type":"null_resource","name":"run_destroy_command","provider_config_key":"null","provisioners":[{"type":"local-exec","expressions":{"command":{"references":["self.triggers.gcloud_bin_abs_path","self.triggers","self","self.triggers.destroy_cmd_entrypoint","self.triggers","self","self.triggers.destroy_cmd_body","self.triggers","self"]}}}],"expressions":{"triggers":{"references":["var.destroy_cmd_entrypoint","var.destroy_cmd_body","local.gcloud_bin_abs_path","var.create_cmd_triggers"]}},"schema_version":0,"count_expression":{"references":["var.enabled"]},"depends_on":["null_resource.module_depends_on","null_resource.decompress","null_resource.additional_components","null_resource.gcloud_auth_google_credentials","null_resource.gcloud_auth_service_account_key_file"]},{"address":"null_resource.upgrade","mode":"managed","type":"null_resource","name":"upgrade","provider_config_key":"null","provisioners":[{"type":"local-exec","expressions":{"command":{"references":["self.triggers.upgrade_command","self.triggers","self"]}}}],"expressions":{"triggers":{"references":["var.create_cmd_entrypoint","var.create_cmd_body","local.upgrade_command","var.create_cmd_triggers"]}},"schema_version":0,"count_expression":{"references":["var.enabled","var.upgrade","local.skip_download"]},"depends_on":["null_resource.decompress"]},{"address":"null_resource.upgrade_destroy","mode":"managed","type":"null_resource","name":"upgrade_destroy","provider_config_key":"null","provisioners":[{"type":"local-exec","expressions":{"command":{"references":["self.triggers.upgrade_command","self.triggers","self"]}}}],"expressions":{"triggers":{"references":["local.upgrade_command"]}},"schema_version":0,"count_expression":{"references":["var.enabled","var.upgrade","local.skip_download"]},"depends_on":["null_resource.additional_components_destroy","null_resource.gcloud_auth_service_account_key_file_destroy","null_resource.gcloud_auth_google_credentials_destroy"]},{"address":"random_id.cache","mode":"managed","type":"random_id","name":"cache","provider_config_key":"module.gcloud_add_ssh_key_metadata:random","expressions":{"byte_length":{"constant_value":4}},"schema_version":0,"count_expression":{"references":["local.skip_download"]}},{"address":"data.external.env_override","mode":"data","type":"external","name":"env_override","provider_config_key":"module.gcloud_add_ssh_key_metadata:external","expressions":{"program":{"references":["path.module"]},"query":{"constant_value":{}}},"schema_version":0,"count_expression":{"references":["var.enabled"]}}],"variables":{"activate_service_account":{"default":true,"description":"Set to false to skip running `gcloud auth activate-service-account`. Optional."},"additional_components":{"default":[],"description":"Additional gcloud CLI components to install. Defaults to none. Valid value are components listed in `gcloud components list`"},"create_cmd_body":{"default":"info","description":"On create, the command body you'd like to run with your entrypoint."},"create_cmd_entrypoint":{"default":"gcloud","description":"On create, the command entrypoint you'd like to use. Can also be set to a custom script. Module's bin directory will be prepended to path."},"create_cmd_triggers":{"default":{},"description":"List of any additional triggers to re-run the create command execution when either of values in the maps change. Some keys are reserved and will be overwritten if specified in this option. (eg. `md5`, `arguments`, `download_gcloud_command`, `download_jq_command`, etc. See details in [the source](https://github.com/terraform-google-modules/terraform-google-gcloud/blob/master/main.tf).)"},"destroy_cmd_body":{"default":"info","description":"On destroy, the command body you'd like to run with your entrypoint."},"destroy_cmd_entrypoint":{"default":"gcloud","description":"On destroy, the command entrypoint you'd like to use.  Can also be set to a custom script. Module's bin directory will be prepended to path."},"enabled":{"default":true,"description":"Flag to optionally disable usage of this module."},"gcloud_download_url":{"default":"","description":"Custom gcloud download url. Optional."},"gcloud_sdk_version":{"default":"481.0.0","description":"The gcloud sdk version to download."},"jq_download_url":{"default":"","description":"Custom jq download url. Optional."},"jq_version":{"default":"1.6","description":"The jq version to download."},"module_depends_on":{"default":[],"description":"List of modules or resources this module depends on."},"platform":{"default":"linux","description":"Platform CLI will run on. Defaults to linux. Valid values: linux, darwin"},"service_account_key_file":{"default":"","description":"Path to service account key file to run `gcloud auth activate-service-account` with. Optional."},"skip_download":{"default":true,"description":"Whether to skip downloading gcloud (assumes gcloud is already available outside the module)"},"upgrade":{"default":true,"description":"Whether to upgrade gcloud at runtime"},"use_tf_google_credentials_env_var":{"default":false,"description":"Use `GOOGLE_CREDENTIALS` environment variable to run `gcloud auth activate-service-account` with. Optional."}}},"version_constraint":"3.5.0"}},"variables":{"cluster_yaml_path":{"default":"../../resources/.cluster1.yaml","description":"Path to the YAML configuration file describing the Anthos cluster"},"credentials_file":{"description":"    Path to the Google Cloud Service Account key file.\n    This is the key that will be used to authenticate the provider with the Cloud APIs\n"},"hostname":{"description":"Hostname of the target VM"},"init_check_script":{"default":"../../resources/run_initialization_checks.sh","description":"Path to the script that validates if the initialization is complete"},"init_logs":{"default":"init.log","description":"Name of the file to write the logs of the initialization script"},"init_script":{"default":"../../resources/init_vm.sh","description":"Path to the initilization script that is to be run on the target VM"},"init_vars_file":{"description":"Path to the file containing the host specific arguments to the init script"},"install_abm_script":{"default":"../../resources/install_abm.sh","description":"Path to the script that installs Anthos on bare metal"},"login_script":{"default":"../../resources/login.sh","description":"Path to the script that generates the token used to login to the Anthos bare metal cluster"},"module_depends_on":{"default":[],"description":"List of modules or resources this module depends on."},"nfs_yaml_path":{"default":"../../resources/.nfs-csi.yaml","description":"Path to the NFS YAML configuration file for the Anthos cluster"},"priv_key_path_template":{"default":"../../resources/.ssh-key-%s.priv","description":"Template denoting the path where the private key is to be stored"},"project_id":{"description":"Google Cloud Project where the target resources live"},"pub_key_path_template":{"default":"../../resources/.ssh-key-%s.pub","description":"Template denoting the path where the public key is to be stored"},"publicIp":{"description":"Publicly accessible IP address of the target VM"},"resources_path":{"description":"Path to the resources folder with the template files"},"username":{"default":"tfadmin","description":"The name of the user to be created to execute the init script"},"zone":{"default":"us-central1-a","description":"Google Cloud Zone where the target VM is in"}}}},"relevant_attributes":[{"resource":"local_file.temp_ssh_priv_key_file","attribute":[]},{"resource":"local_file.temp_ssh_pub_key_file","attribute":[]},{"resource":"module.gcloud_add_ssh_key_metadata.data.external.env_override[0]","attribute":["result","download"]},{"resource":"module.gcloud_add_ssh_key_metadata.null_resource.additional_components","attribute":[]},{"resource":"module.gcloud_add_ssh_key_metadata.null_resource.gcloud_auth_google_credentials","attribute":[]},{"resource":"module.gcloud_add_ssh_key_metadata.null_resource.gcloud_auth_service_account_key_file","attribute":[]},{"resource":"module.gcloud_add_ssh_key_metadata.null_resource.run_command","attribute":[]},{"resource":"module.gcloud_add_ssh_key_metadata.null_resource.run_destroy_command","attribute":[]},{"resource":"module.gcloud_add_ssh_key_metadata.random_id.cache[0]","attribute":["hex"]},{"resource":"tls_private_key.ssh_key_pair","attribute":["public_key_openssh"]},{"resource":"tls_private_key.ssh_key_pair","attribute":["private_key_pem"]}],"timestamp":"2025-11-08T21:21:51Z","errored":false}